{
    "CoordinateSystemType": "Unknown",
    "SectorType": 1,
    "city": "Berßel",
    "comments": null,
    "containerShape": null,
    "coordinates": "51.9557000,10.7526800",
    "dateEnd": "04/17/2024 12:40:00",
    "dateStart": "04/17/2024 09:40:00",
    "definition": null,
    "district": null,
    "geoType": 2,
    "houseNr": null,
    "id": 4085123,
    "idPublic": null,
    "internal": 0,
    "isFixed": false,
    "isOutageInArea": false,
    "lastUpdate": "04/17/2024 20:55:03",
    "liveInfo": null,
    "operatorId": 42,
    "operatorName": "Avacon AG",
    "origin": 1,
    "photo": null,
    "postalCode": "38835",
    "radius": 1000,
    "social": null,
    "socialText": null,
    "street": null,
    "subsection": null,
    "type": 1
}