{
    "CoordinateSystemType": "Unknown",
    "SectorType": 1,
    "city": "Pillig",
    "comments": null,
    "containerShape": null,
    "coordinates": "50.24526248799722,7.311745717087252",
    "dateEnd": "07/23/2024 17:55:24",
    "dateStart": "07/22/2024 16:40:40",
    "definition": null,
    "district": null,
    "geoType": 1,
    "houseNr": null,
    "id": 4255693,
    "idPublic": null,
    "internal": 0,
    "isFixed": false,
    "isOutageInArea": false,
    "lastUpdate": "07/23/2024 17:55:24",
    "liveInfo": null,
    "operatorId": 132,
    "operatorName": "Westnetz GmbH",
    "origin": 5,
    "photo": null,
    "postalCode": "56753",
    "radius": null,
    "social": null,
    "socialText": null,
    "street": null,
    "subsection": null,
    "type": 1
}