{
    "CoordinateSystemType": "Unknown",
    "SectorType": 1,
    "city": "Massing",
    "comments": null,
    "containerShape": null,
    "coordinates": "48.3802000,12.6443000",
    "dateEnd": "07/15/2024 20:55:21",
    "dateStart": "07/15/2024 12:52:27",
    "definition": null,
    "district": null,
    "geoType": 2,
    "houseNr": null,
    "id": 4243748,
    "idPublic": null,
    "internal": 0,
    "isFixed": false,
    "isOutageInArea": false,
    "lastUpdate": "07/15/2024 20:55:21",
    "liveInfo": null,
    "operatorId": 402,
    "operatorName": "Bayernwerk Netz GmbH",
    "origin": 1,
    "photo": null,
    "postalCode": "84323",
    "radius": 1000,
    "social": null,
    "socialText": null,
    "street": null,
    "subsection": null,
    "type": 1
}