{
    "CoordinateSystemType": "Unknown",
    "SectorType": 1,
    "city": "Plaidt",
    "comments": null,
    "containerShape": null,
    "coordinates": "50.39307180225939,7.4030308417027",
    "dateEnd": "10/26/2023 15:00:50",
    "dateStart": "10/25/2023 12:30:00",
    "definition": null,
    "district": null,
    "geoType": 1,
    "houseNr": null,
    "id": 3900262,
    "idPublic": null,
    "internal": 0,
    "isFixed": false,
    "isOutageInArea": false,
    "lastUpdate": "10/26/2023 15:00:50",
    "liveInfo": null,
    "operatorId": 132,
    "operatorName": "Westnetz GmbH",
    "origin": 5,
    "photo": null,
    "postalCode": "56637",
    "radius": null,
    "social": null,
    "socialText": null,
    "street": null,
    "subsection": null,
    "type": 2
}