{
    "CoordinateSystemType": "Unknown",
    "SectorType": 1,
    "city": "Siegen",
    "comments": null,
    "containerShape": null,
    "coordinates": "50.869931,8.05591498896718",
    "dateEnd": "09/24/2024 15:04:23",
    "dateStart": "09/24/2024 15:09:09",
    "definition": null,
    "district": null,
    "geoType": 1,
    "houseNr": null,
    "id": 4394475,
    "idPublic": null,
    "internal": 0,
    "isFixed": true,
    "isOutageInArea": false,
    "lastUpdate": "09/24/2024 15:17:05",
    "liveInfo": null,
    "operatorId": 132,
    "operatorName": "Westnetz GmbH",
    "origin": 5,
    "photo": null,
    "postalCode": "57074",
    "radius": null,
    "social": null,
    "socialText": null,
    "street": null,
    "subsection": null,
    "type": 1
}