{
    "CoordinateSystemType": "Unknown",
    "SectorType": 1,
    "city": "Raesfeld",
    "comments": null,
    "containerShape": null,
    "coordinates": "51.76831711513977,6.855424044433946",
    "dateEnd": "03/07/2024 13:57:30",
    "dateStart": "03/06/2024 07:54:00",
    "definition": null,
    "district": null,
    "geoType": 1,
    "houseNr": null,
    "id": 4020062,
    "idPublic": null,
    "internal": 0,
    "isFixed": false,
    "isOutageInArea": false,
    "lastUpdate": "03/07/2024 13:57:30",
    "liveInfo": null,
    "operatorId": 132,
    "operatorName": "Westnetz GmbH",
    "origin": 5,
    "photo": null,
    "postalCode": "46348",
    "radius": null,
    "social": null,
    "socialText": null,
    "street": null,
    "subsection": null,
    "type": 2
}