{
    "CoordinateSystemType": "Unknown",
    "SectorType": 1,
    "city": "Seeshaupt",
    "comments": null,
    "containerShape": null,
    "coordinates": "47.81948846481186,11.283746294554108",
    "dateEnd": "12/02/2023 01:30:00",
    "dateStart": "12/01/2023 23:25:03",
    "definition": null,
    "district": null,
    "geoType": 1,
    "houseNr": null,
    "id": 3922791,
    "idPublic": null,
    "internal": 0,
    "isFixed": false,
    "isOutageInArea": false,
    "lastUpdate": "12/02/2023 00:58:33",
    "liveInfo": null,
    "operatorId": 402,
    "operatorName": "Bayernwerk Netz GmbH",
    "origin": 3,
    "photo": null,
    "postalCode": "82402",
    "radius": null,
    "social": null,
    "socialText": null,
    "street": null,
    "subsection": null,
    "type": 1
}