{
    "CoordinateSystemType": "Unknown",
    "SectorType": 1,
    "city": "Laboe",
    "comments": null,
    "containerShape": null,
    "coordinates": "54.40730321893782,10.250227200991844",
    "dateEnd": "08/26/2024 22:35:00",
    "dateStart": "08/26/2024 20:33:48",
    "definition": null,
    "district": null,
    "geoType": 1,
    "houseNr": null,
    "id": 4319443,
    "idPublic": null,
    "internal": 0,
    "isFixed": false,
    "isOutageInArea": false,
    "lastUpdate": "08/26/2024 20:51:48",
    "liveInfo": null,
    "operatorId": 120,
    "operatorName": "Schleswig-Holstein Netz AG",
    "origin": 3,
    "photo": null,
    "postalCode": "24235",
    "radius": null,
    "social": null,
    "socialText": null,
    "street": null,
    "subsection": null,
    "type": 1
}