{
    "CoordinateSystemType": "Unknown",
    "SectorType": 1,
    "city": "Sanitz",
    "comments": null,
    "containerShape": null,
    "coordinates": "54.0462286,12.3653082",
    "dateEnd": "09/14/2024 15:58:00",
    "dateStart": "09/14/2024 14:28:00",
    "definition": null,
    "district": null,
    "geoType": 1,
    "houseNr": null,
    "id": 4423984,
    "idPublic": null,
    "internal": 0,
    "isFixed": false,
    "isOutageInArea": false,
    "lastUpdate": "10/01/2024 03:20:24",
    "liveInfo": null,
    "operatorId": 81,
    "operatorName": "E.DIS Netz GmbH",
    "origin": 1,
    "photo": null,
    "postalCode": "18190",
    "radius": 1000,
    "social": null,
    "socialText": null,
    "street": null,
    "subsection": null,
    "type": 1
}