{
    "CoordinateSystemType": "Unknown",
    "SectorType": 1,
    "city": "Much",
    "comments": null,
    "containerShape": null,
    "coordinates": "50.86305920015354,7.434471917559086",
    "dateEnd": "08/17/2024 03:16:06",
    "dateStart": "07/31/2024 00:32:03",
    "definition": null,
    "district": null,
    "geoType": 1,
    "houseNr": null,
    "id": 4270347,
    "idPublic": null,
    "internal": 0,
    "isFixed": false,
    "isOutageInArea": false,
    "lastUpdate": "08/17/2024 03:16:06",
    "liveInfo": null,
    "operatorId": 132,
    "operatorName": "Westnetz GmbH",
    "origin": 5,
    "photo": null,
    "postalCode": "53804",
    "radius": null,
    "social": null,
    "socialText": null,
    "street": null,
    "subsection": null,
    "type": 1
}