{
    "CoordinateSystemType": "Unknown",
    "SectorType": 1,
    "city": "Ochsenhausen",
    "comments": null,
    "containerShape": null,
    "coordinates": "48.08667279273759,9.9455016",
    "dateEnd": "07/31/2024 22:00:00",
    "dateStart": "07/31/2024 19:57:22",
    "definition": null,
    "district": null,
    "geoType": 1,
    "houseNr": null,
    "id": 4271788,
    "idPublic": null,
    "internal": 0,
    "isFixed": false,
    "isOutageInArea": false,
    "lastUpdate": "07/31/2024 19:57:23",
    "liveInfo": null,
    "operatorId": 411,
    "operatorName": "Netze BW GmbH",
    "origin": 3,
    "photo": null,
    "postalCode": "88416",
    "radius": null,
    "social": null,
    "socialText": null,
    "street": null,
    "subsection": null,
    "type": 1
}