{
    "CoordinateSystemType": "Unknown",
    "SectorType": 1,
    "city": "Wolnzach",
    "comments": null,
    "containerShape": null,
    "coordinates": "48.6120000,11.6188000",
    "dateEnd": "08/04/2024 05:55:22",
    "dateStart": "07/31/2024 15:38:38",
    "definition": null,
    "district": null,
    "geoType": 2,
    "houseNr": null,
    "id": 4271589,
    "idPublic": null,
    "internal": 0,
    "isFixed": false,
    "isOutageInArea": false,
    "lastUpdate": "08/04/2024 05:55:22",
    "liveInfo": null,
    "operatorId": 402,
    "operatorName": "Bayernwerk Netz GmbH",
    "origin": 1,
    "photo": null,
    "postalCode": "85283",
    "radius": 1000,
    "social": null,
    "socialText": null,
    "street": null,
    "subsection": null,
    "type": 1
}