{
    "CoordinateSystemType": "Unknown",
    "SectorType": 1,
    "city": "Lollar",
    "comments": null,
    "containerShape": null,
    "coordinates": "50.6586166211204,8.69936277972473",
    "dateEnd": "06/19/2024 05:53:02",
    "dateStart": "06/18/2024 13:55:13",
    "definition": null,
    "district": "Odenhausen",
    "geoType": 2,
    "houseNr": null,
    "id": 4193412,
    "idPublic": null,
    "internal": 0,
    "isFixed": false,
    "isOutageInArea": false,
    "lastUpdate": "06/19/2024 05:53:02",
    "liveInfo": null,
    "operatorId": 216,
    "operatorName": "EAM Netz GmbH",
    "origin": 5,
    "photo": null,
    "postalCode": "35457",
    "radius": 500,
    "social": null,
    "socialText": null,
    "street": null,
    "subsection": null,
    "type": 1
}