{
    "CoordinateSystemType": "Unknown",
    "SectorType": 1,
    "city": "Grosselfingen",
    "comments": null,
    "containerShape": null,
    "coordinates": "48.325090828847124,8.88246202330841",
    "dateEnd": "08/10/2024 08:57:04",
    "dateStart": "08/09/2024 16:31:20",
    "definition": null,
    "district": null,
    "geoType": 1,
    "houseNr": null,
    "id": 4285975,
    "idPublic": null,
    "internal": 0,
    "isFixed": false,
    "isOutageInArea": false,
    "lastUpdate": "08/10/2024 08:57:04",
    "liveInfo": "",
    "operatorId": 411,
    "operatorName": "Netze BW GmbH",
    "origin": 5,
    "photo": null,
    "postalCode": "72415",
    "radius": null,
    "social": null,
    "socialText": null,
    "street": null,
    "subsection": null,
    "type": 1
}