{
    "CoordinateSystemType": "Unknown",
    "SectorType": 1,
    "city": "Zettlitz",
    "comments": null,
    "containerShape": null,
    "coordinates": "51.07993592043809,12.841350420053576",
    "dateEnd": "02/12/2024 15:00:00",
    "dateStart": "02/12/2024 12:30:00",
    "definition": null,
    "district": "Zettlitz",
    "geoType": 1,
    "houseNr": null,
    "id": 3989245,
    "idPublic": null,
    "internal": 0,
    "isFixed": false,
    "isOutageInArea": false,
    "lastUpdate": "02/12/2024 13:55:54",
    "liveInfo": null,
    "operatorId": 6,
    "operatorName": "Mitteldeutsche Netzgesellschaft Strom mbH",
    "origin": 5,
    "photo": null,
    "postalCode": "09306",
    "radius": null,
    "social": null,
    "socialText": null,
    "street": null,
    "subsection": null,
    "type": 2
}