{
    "CoordinateSystemType": "Unknown",
    "SectorType": 1,
    "city": "Guldental",
    "comments": null,
    "containerShape": null,
    "coordinates": "49.89201221480742,7.878489094893058",
    "dateEnd": "06/05/2024 23:57:06",
    "dateStart": "06/05/2024 09:07:40",
    "definition": null,
    "district": null,
    "geoType": 1,
    "houseNr": null,
    "id": 4166104,
    "idPublic": null,
    "internal": 0,
    "isFixed": false,
    "isOutageInArea": false,
    "lastUpdate": "06/05/2024 23:57:06",
    "liveInfo": null,
    "operatorId": 132,
    "operatorName": "Westnetz GmbH",
    "origin": 5,
    "photo": null,
    "postalCode": "55452",
    "radius": null,
    "social": null,
    "socialText": null,
    "street": null,
    "subsection": null,
    "type": 1
}