{
    "CoordinateSystemType": "Unknown",
    "SectorType": 1,
    "city": "Verl",
    "comments": null,
    "containerShape": null,
    "coordinates": "51.85174128467502,8.555871339048807",
    "dateEnd": "06/06/2024 05:57:06",
    "dateStart": "06/05/2024 12:30:00",
    "definition": null,
    "district": null,
    "geoType": 1,
    "houseNr": null,
    "id": 4166664,
    "idPublic": null,
    "internal": 0,
    "isFixed": false,
    "isOutageInArea": false,
    "lastUpdate": "06/06/2024 05:57:06",
    "liveInfo": null,
    "operatorId": 132,
    "operatorName": "Westnetz GmbH",
    "origin": 5,
    "photo": null,
    "postalCode": "33415",
    "radius": null,
    "social": null,
    "socialText": null,
    "street": null,
    "subsection": null,
    "type": 2
}