{
    "CoordinateSystemType": "Unknown",
    "SectorType": 1,
    "city": "Bremen",
    "comments": null,
    "containerShape": null,
    "coordinates": "53.067260,8.800200",
    "dateEnd": "06/06/2024 07:52:03",
    "dateStart": "06/05/2024 09:45:20",
    "definition": null,
    "district": "Südervorstadt",
    "geoType": 2,
    "houseNr": null,
    "id": 4166270,
    "idPublic": null,
    "internal": 0,
    "isFixed": false,
    "isOutageInArea": false,
    "lastUpdate": "06/06/2024 07:52:03",
    "liveInfo": "Störungsbedingte Unterbechung Lehnstedter Str.",
    "operatorId": 182,
    "operatorName": "wesernetz Bremen GmbH",
    "origin": 5,
    "photo": null,
    "postalCode": "28201",
    "radius": 300,
    "social": null,
    "socialText": null,
    "street": null,
    "subsection": null,
    "type": 1
}