{
    "CoordinateSystemType": "Unknown",
    "SectorType": 1,
    "city": "Plauen",
    "comments": null,
    "containerShape": null,
    "coordinates": "50.521433242966616,12.11779510079084",
    "dateEnd": "07/02/2024 20:57:06",
    "dateStart": "07/02/2024 08:30:00",
    "definition": null,
    "district": "Plauen",
    "geoType": 1,
    "houseNr": null,
    "id": 4221038,
    "idPublic": null,
    "internal": 0,
    "isFixed": false,
    "isOutageInArea": false,
    "lastUpdate": "07/02/2024 20:57:06",
    "liveInfo": null,
    "operatorId": 6,
    "operatorName": "Mitteldeutsche Netzgesellschaft Strom mbH",
    "origin": 5,
    "photo": null,
    "postalCode": "08525",
    "radius": null,
    "social": null,
    "socialText": null,
    "street": null,
    "subsection": null,
    "type": 2
}