{
    "CoordinateSystemType": "Unknown",
    "SectorType": 1,
    "city": "Münster",
    "comments": null,
    "containerShape": null,
    "coordinates": "51.95815629440055,7.616594561242003",
    "dateEnd": "09/04/2024 21:45:00",
    "dateStart": "09/04/2024 19:42:22",
    "definition": null,
    "district": null,
    "geoType": 1,
    "houseNr": null,
    "id": 4337592,
    "idPublic": null,
    "internal": 0,
    "isFixed": false,
    "isOutageInArea": false,
    "lastUpdate": "09/04/2024 20:57:39",
    "liveInfo": null,
    "operatorId": 324,
    "operatorName": "Stadtnetze Münster GmbH",
    "origin": 3,
    "photo": null,
    "postalCode": "48149",
    "radius": null,
    "social": null,
    "socialText": null,
    "street": null,
    "subsection": null,
    "type": 1
}