{
    "CoordinateSystemType": "Unknown",
    "SectorType": 1,
    "city": "Neukirchen/Erzgebirge",
    "comments": null,
    "containerShape": null,
    "coordinates": null,
    "dateEnd": "08/12/2024 17:56:11",
    "dateStart": "08/10/2024 08:01:48",
    "definition": null,
    "district": "Neukirchen/Erzgebirge",
    "geoType": 1,
    "houseNr": null,
    "id": 4286839,
    "idPublic": null,
    "internal": 0,
    "isFixed": false,
    "isOutageInArea": false,
    "lastUpdate": "08/12/2024 17:56:11",
    "liveInfo": null,
    "operatorId": 6,
    "operatorName": "Mitteldeutsche Netzgesellschaft Strom mbH",
    "origin": 5,
    "photo": null,
    "postalCode": "09221",
    "radius": null,
    "social": null,
    "socialText": null,
    "street": null,
    "subsection": null,
    "type": 1
}