{
    "CoordinateSystemType": "Unknown",
    "SectorType": 1,
    "city": "Neu-Seeland",
    "comments": null,
    "containerShape": null,
    "coordinates": "51.61494946828257,14.166319762730984",
    "dateEnd": "06/26/2024 05:53:07",
    "dateStart": "06/25/2024 07:30:00",
    "definition": null,
    "district": "Ressen",
    "geoType": 1,
    "houseNr": null,
    "id": 4208017,
    "idPublic": null,
    "internal": 0,
    "isFixed": false,
    "isOutageInArea": false,
    "lastUpdate": "06/26/2024 05:53:07",
    "liveInfo": null,
    "operatorId": 6,
    "operatorName": "Mitteldeutsche Netzgesellschaft Strom mbH",
    "origin": 5,
    "photo": null,
    "postalCode": "03103",
    "radius": null,
    "social": null,
    "socialText": null,
    "street": null,
    "subsection": null,
    "type": 2
}