{
    "CoordinateSystemType": "Unknown",
    "SectorType": 1,
    "city": "Nienburg/Saale",
    "comments": null,
    "containerShape": null,
    "coordinates": null,
    "dateEnd": "08/10/2024 20:56:55",
    "dateStart": "08/02/2024 10:30:00",
    "definition": null,
    "district": "Nienburg/Saale",
    "geoType": 1,
    "houseNr": null,
    "id": 4274371,
    "idPublic": null,
    "internal": 0,
    "isFixed": false,
    "isOutageInArea": false,
    "lastUpdate": "08/10/2024 20:56:55",
    "liveInfo": null,
    "operatorId": 6,
    "operatorName": "Mitteldeutsche Netzgesellschaft Strom mbH",
    "origin": 5,
    "photo": null,
    "postalCode": "06429",
    "radius": null,
    "social": null,
    "socialText": null,
    "street": null,
    "subsection": null,
    "type": 2
}