{
    "CoordinateSystemType": "Unknown",
    "SectorType": 1,
    "city": "Bad Abbach",
    "comments": null,
    "containerShape": null,
    "coordinates": "48.9409000,12.0566000",
    "dateEnd": "05/23/2024 08:55:41",
    "dateStart": "05/22/2024 09:52:00",
    "definition": null,
    "district": null,
    "geoType": 2,
    "houseNr": null,
    "id": 4141380,
    "idPublic": null,
    "internal": 0,
    "isFixed": false,
    "isOutageInArea": false,
    "lastUpdate": "05/23/2024 08:55:41",
    "liveInfo": null,
    "operatorId": 402,
    "operatorName": "Bayernwerk Netz GmbH",
    "origin": 1,
    "photo": null,
    "postalCode": "93077",
    "radius": 1000,
    "social": null,
    "socialText": null,
    "street": null,
    "subsection": null,
    "type": 1
}