{
    "CoordinateSystemType": "Unknown",
    "SectorType": 1,
    "city": "Vaihingen an der Enz",
    "comments": null,
    "containerShape": null,
    "coordinates": "48.92027965217471,8.987234946157002",
    "dateEnd": "08/18/2024 11:57:06",
    "dateStart": "08/13/2024 19:01:06",
    "definition": null,
    "district": null,
    "geoType": 1,
    "houseNr": null,
    "id": 4294181,
    "idPublic": null,
    "internal": 0,
    "isFixed": false,
    "isOutageInArea": false,
    "lastUpdate": "08/18/2024 11:57:06",
    "liveInfo": "",
    "operatorId": 411,
    "operatorName": "Netze BW GmbH",
    "origin": 5,
    "photo": null,
    "postalCode": "71665",
    "radius": null,
    "social": null,
    "socialText": null,
    "street": null,
    "subsection": null,
    "type": 1
}