{
    "CoordinateSystemType": "Unknown",
    "SectorType": 1,
    "city": "Schmallenberg",
    "comments": null,
    "containerShape": null,
    "coordinates": "51.195353511552476,8.316893647913615",
    "dateEnd": "03/10/2024 10:56:01",
    "dateStart": "03/09/2024 23:14:26",
    "definition": null,
    "district": null,
    "geoType": 1,
    "houseNr": null,
    "id": 4025932,
    "idPublic": null,
    "internal": 0,
    "isFixed": false,
    "isOutageInArea": false,
    "lastUpdate": "03/10/2024 10:56:01",
    "liveInfo": null,
    "operatorId": 132,
    "operatorName": "Westnetz GmbH",
    "origin": 5,
    "photo": null,
    "postalCode": "57392",
    "radius": null,
    "social": null,
    "socialText": null,
    "street": null,
    "subsection": null,
    "type": 1
}