{
    "CoordinateSystemType": "Unknown",
    "SectorType": 1,
    "city": "Gelsenkirchen",
    "comments": null,
    "containerShape": null,
    "coordinates": "51.548655003031286,7.04643014642315",
    "dateEnd": "09/26/2024 14:59:25",
    "dateStart": "09/26/2024 14:24:00",
    "definition": null,
    "district": null,
    "geoType": 1,
    "houseNr": null,
    "id": 4403054,
    "idPublic": null,
    "internal": 0,
    "isFixed": true,
    "isOutageInArea": false,
    "lastUpdate": "09/26/2024 14:59:25",
    "liveInfo": null,
    "operatorId": 308,
    "operatorName": "ELE Verteilnetz GmbH",
    "origin": 5,
    "photo": null,
    "postalCode": "45899",
    "radius": null,
    "social": null,
    "socialText": null,
    "street": null,
    "subsection": null,
    "type": 1
}