{
    "CoordinateSystemType": "Unknown",
    "SectorType": 1,
    "city": "Winterberg",
    "comments": null,
    "containerShape": null,
    "coordinates": "51.252785,8.472342246894122",
    "dateEnd": "09/28/2024 19:24:28",
    "dateStart": "09/28/2024 19:09:40",
    "definition": null,
    "district": null,
    "geoType": 1,
    "houseNr": null,
    "id": 4413054,
    "idPublic": null,
    "internal": 0,
    "isFixed": true,
    "isOutageInArea": false,
    "lastUpdate": "09/28/2024 19:24:28",
    "liveInfo": null,
    "operatorId": 132,
    "operatorName": "Westnetz GmbH",
    "origin": 5,
    "photo": null,
    "postalCode": "59955",
    "radius": null,
    "social": null,
    "socialText": null,
    "street": null,
    "subsection": null,
    "type": 1
}