{
    "CoordinateSystemType": "Unknown",
    "SectorType": 1,
    "city": "Annweiler am Trifels",
    "comments": null,
    "containerShape": null,
    "coordinates": "49.22115570121376,8.016196925275533",
    "dateEnd": "08/19/2024 12:51:31",
    "dateStart": "08/19/2024 03:59:47",
    "definition": null,
    "district": null,
    "geoType": 1,
    "houseNr": null,
    "id": 4304781,
    "idPublic": null,
    "internal": 0,
    "isFixed": false,
    "isOutageInArea": false,
    "lastUpdate": "08/19/2024 12:51:32",
    "liveInfo": "Stromausfall im Regionalnetz! Die Techniker sind bereits im Einsatz.",
    "operatorId": 368,
    "operatorName": "Pfalzwerke Netz AG",
    "origin": 5,
    "photo": null,
    "postalCode": "76855",
    "radius": null,
    "social": null,
    "socialText": null,
    "street": null,
    "subsection": null,
    "type": 1
}