{
    "CoordinateSystemType": "Unknown",
    "SectorType": 1,
    "city": "Essen",
    "comments": null,
    "containerShape": null,
    "coordinates": "51.51019774335431,7.039588223156944",
    "dateEnd": "08/19/2024 23:56:09",
    "dateStart": "08/19/2024 09:30:50",
    "definition": null,
    "district": null,
    "geoType": 1,
    "houseNr": null,
    "id": 4305680,
    "idPublic": null,
    "internal": 0,
    "isFixed": false,
    "isOutageInArea": false,
    "lastUpdate": "08/19/2024 23:56:09",
    "liveInfo": null,
    "operatorId": 132,
    "operatorName": "Westnetz GmbH",
    "origin": 5,
    "photo": null,
    "postalCode": "45327",
    "radius": null,
    "social": null,
    "socialText": null,
    "street": null,
    "subsection": null,
    "type": 1
}