{
    "CoordinateSystemType": "Unknown",
    "SectorType": 1,
    "city": "Wendeburg",
    "comments": null,
    "containerShape": null,
    "coordinates": "52.3440873,10.3208697",
    "dateEnd": "09/13/2024 17:55:03",
    "dateStart": "09/12/2024 10:50:00",
    "definition": null,
    "district": null,
    "geoType": 2,
    "houseNr": null,
    "id": 4352443,
    "idPublic": null,
    "internal": 0,
    "isFixed": false,
    "isOutageInArea": false,
    "lastUpdate": "09/13/2024 17:55:03",
    "liveInfo": null,
    "operatorId": 42,
    "operatorName": "Avacon AG",
    "origin": 1,
    "photo": null,
    "postalCode": "38176",
    "radius": 1000,
    "social": null,
    "socialText": null,
    "street": null,
    "subsection": null,
    "type": 1
}