{
    "CoordinateSystemType": "Unknown",
    "SectorType": 1,
    "city": "Hugoldsdorf",
    "comments": null,
    "containerShape": null,
    "coordinates": "54.12883427109745,12.751726435556428",
    "dateEnd": "08/05/2024 22:40:00",
    "dateStart": "08/05/2024 20:36:13",
    "definition": null,
    "district": null,
    "geoType": 1,
    "houseNr": null,
    "id": 4278003,
    "idPublic": null,
    "internal": 0,
    "isFixed": false,
    "isOutageInArea": false,
    "lastUpdate": "08/05/2024 20:36:14",
    "liveInfo": null,
    "operatorId": 81,
    "operatorName": "E.DIS Netz GmbH",
    "origin": 3,
    "photo": null,
    "postalCode": "18465",
    "radius": null,
    "social": null,
    "socialText": null,
    "street": null,
    "subsection": null,
    "type": 1
}