{
    "CoordinateSystemType": "Unknown",
    "SectorType": 1,
    "city": "Nideggen",
    "comments": null,
    "containerShape": null,
    "coordinates": "50.65881606348726,6.4065852153622735",
    "dateEnd": "04/09/2024 05:56:18",
    "dateStart": "04/08/2024 22:20:31",
    "definition": null,
    "district": null,
    "geoType": 1,
    "houseNr": null,
    "id": 4069986,
    "idPublic": null,
    "internal": 0,
    "isFixed": false,
    "isOutageInArea": false,
    "lastUpdate": "04/09/2024 05:56:18",
    "liveInfo": null,
    "operatorId": 132,
    "operatorName": "Westnetz GmbH",
    "origin": 5,
    "photo": null,
    "postalCode": "52385",
    "radius": null,
    "social": null,
    "socialText": null,
    "street": null,
    "subsection": null,
    "type": 1
}