{
    "CoordinateSystemType": "Unknown",
    "SectorType": 1,
    "city": "Plochingen",
    "comments": null,
    "containerShape": null,
    "coordinates": "48.7202982306185,9.429518741057109",
    "dateEnd": "08/25/2024 14:54:26",
    "dateStart": "08/25/2024 10:36:41",
    "definition": null,
    "district": null,
    "geoType": 1,
    "houseNr": null,
    "id": 4316631,
    "idPublic": null,
    "internal": 0,
    "isFixed": false,
    "isOutageInArea": false,
    "lastUpdate": "08/25/2024 14:54:26",
    "liveInfo": "",
    "operatorId": 411,
    "operatorName": "Netze BW GmbH",
    "origin": 5,
    "photo": null,
    "postalCode": "73207",
    "radius": null,
    "social": null,
    "socialText": null,
    "street": null,
    "subsection": null,
    "type": 1
}