{
    "CoordinateSystemType": "Unknown",
    "SectorType": 1,
    "city": "Postbauer-Heng",
    "comments": null,
    "containerShape": null,
    "coordinates": "49.296558632853184,11.353085802819495",
    "dateEnd": "05/21/2024 19:00:00",
    "dateStart": "05/21/2024 16:57:13",
    "definition": null,
    "district": null,
    "geoType": 1,
    "houseNr": null,
    "id": 4139791,
    "idPublic": null,
    "internal": 0,
    "isFixed": false,
    "isOutageInArea": false,
    "lastUpdate": "05/21/2024 18:12:21",
    "liveInfo": null,
    "operatorId": 402,
    "operatorName": "Bayernwerk Netz GmbH",
    "origin": 3,
    "photo": null,
    "postalCode": "92353",
    "radius": null,
    "social": null,
    "socialText": null,
    "street": null,
    "subsection": null,
    "type": 1
}