{
    "CoordinateSystemType": "Unknown",
    "SectorType": 1,
    "city": "Meßkirch",
    "comments": null,
    "containerShape": null,
    "coordinates": "48.00381007761007,9.150142412601706",
    "dateEnd": "08/23/2024 08:57:23",
    "dateStart": "08/22/2024 14:39:40",
    "definition": null,
    "district": null,
    "geoType": 1,
    "houseNr": null,
    "id": 4312159,
    "idPublic": null,
    "internal": 0,
    "isFixed": false,
    "isOutageInArea": false,
    "lastUpdate": "08/23/2024 08:57:23",
    "liveInfo": "",
    "operatorId": 411,
    "operatorName": "Netze BW GmbH",
    "origin": 5,
    "photo": null,
    "postalCode": "88605",
    "radius": null,
    "social": null,
    "socialText": null,
    "street": null,
    "subsection": null,
    "type": 1
}