{
    "CoordinateSystemType": "Unknown",
    "SectorType": 1,
    "city": "Vorderweidenthal",
    "comments": null,
    "containerShape": null,
    "coordinates": "49.12919169553548,7.881271449105871",
    "dateEnd": "06/27/2024 11:12:49",
    "dateStart": "06/26/2024 17:16:44",
    "definition": null,
    "district": null,
    "geoType": 1,
    "houseNr": null,
    "id": 4210655,
    "idPublic": null,
    "internal": 0,
    "isFixed": false,
    "isOutageInArea": false,
    "lastUpdate": "06/27/2024 11:12:49",
    "liveInfo": "Stromausfall im Regionalnetz! Die Techniker sind bereits im Einsatz.",
    "operatorId": 368,
    "operatorName": "Pfalzwerke Netz AG",
    "origin": 5,
    "photo": null,
    "postalCode": "76889",
    "radius": null,
    "social": null,
    "socialText": null,
    "street": null,
    "subsection": null,
    "type": 1
}