{
    "CoordinateSystemType": "Unknown",
    "SectorType": 1,
    "city": "Isselburg",
    "comments": null,
    "containerShape": null,
    "coordinates": "51.817261391719754,6.468721530023442",
    "dateEnd": "12/22/2023 02:13:49",
    "dateStart": "12/21/2023 16:58:22",
    "definition": null,
    "district": null,
    "geoType": 1,
    "houseNr": null,
    "id": 3947550,
    "idPublic": null,
    "internal": 0,
    "isFixed": false,
    "isOutageInArea": false,
    "lastUpdate": "12/22/2023 02:13:49",
    "liveInfo": null,
    "operatorId": 132,
    "operatorName": "Westnetz GmbH",
    "origin": 5,
    "photo": null,
    "postalCode": "46419",
    "radius": null,
    "social": null,
    "socialText": null,
    "street": null,
    "subsection": null,
    "type": 1
}