{
    "CoordinateSystemType": "Unknown",
    "SectorType": 1,
    "city": "Freihung",
    "comments": null,
    "containerShape": null,
    "coordinates": "49.6276000,11.9448000",
    "dateEnd": "05/28/2024 11:55:25",
    "dateStart": "05/27/2024 12:48:00",
    "definition": null,
    "district": null,
    "geoType": 2,
    "houseNr": null,
    "id": 4149823,
    "idPublic": null,
    "internal": 0,
    "isFixed": false,
    "isOutageInArea": false,
    "lastUpdate": "05/28/2024 11:55:25",
    "liveInfo": null,
    "operatorId": 402,
    "operatorName": "Bayernwerk Netz GmbH",
    "origin": 1,
    "photo": null,
    "postalCode": "92271",
    "radius": 1000,
    "social": null,
    "socialText": null,
    "street": null,
    "subsection": null,
    "type": 1
}