{
    "CoordinateSystemType": "Unknown",
    "SectorType": 1,
    "city": "Recklinghausen",
    "comments": null,
    "containerShape": null,
    "coordinates": "51.603972319318665,7.171123444522982",
    "dateEnd": "",
    "dateStart": "07/03/2024 08:12:15",
    "definition": null,
    "district": null,
    "geoType": 1,
    "houseNr": null,
    "id": 4223962,
    "idPublic": null,
    "internal": 0,
    "isFixed": false,
    "isOutageInArea": false,
    "lastUpdate": "07/03/2024 17:55:08",
    "liveInfo": null,
    "operatorId": 132,
    "operatorName": "Westnetz GmbH",
    "origin": 5,
    "photo": null,
    "postalCode": "45659",
    "radius": null,
    "social": null,
    "socialText": null,
    "street": null,
    "subsection": null,
    "type": 1
}