{
    "CoordinateSystemType": "Unknown",
    "SectorType": 1,
    "city": "Quedlinburg",
    "comments": null,
    "containerShape": null,
    "coordinates": "51.729126,11.1207775",
    "dateEnd": "07/03/2024 18:00:00",
    "dateStart": "07/03/2024 08:37:32",
    "definition": null,
    "district": null,
    "geoType": 1,
    "houseNr": null,
    "id": 4224005,
    "idPublic": null,
    "internal": 0,
    "isFixed": false,
    "isOutageInArea": false,
    "lastUpdate": "07/03/2024 08:37:32",
    "liveInfo": "",
    "operatorId": 41,
    "operatorName": "Stadtwerke Quedlinburg GmbH",
    "origin": 2,
    "photo": null,
    "postalCode": "06485",
    "radius": 500,
    "social": null,
    "socialText": null,
    "street": "Grünestraße",
    "subsection": null,
    "type": 1
}