{
    "CoordinateSystemType": "Unknown",
    "SectorType": 1,
    "city": "Reutlingen",
    "comments": null,
    "containerShape": null,
    "coordinates": "48.5326848,9.1809341",
    "dateEnd": "12/09/2023 16:00:00",
    "dateStart": "12/09/2023 13:00:00",
    "definition": null,
    "district": null,
    "geoType": 2,
    "houseNr": null,
    "id": 3934369,
    "idPublic": null,
    "internal": 0,
    "isFixed": false,
    "isOutageInArea": false,
    "lastUpdate": "12/09/2023 12:37:02",
    "liveInfo": "Eichgartenhof 3-9/1\r & Eichgartenstraße 1\r & Friedrichstraße 6-10",
    "operatorId": 487,
    "operatorName": "FairNetz GmbH",
    "origin": 5,
    "photo": null,
    "postalCode": "72768",
    "radius": 200,
    "social": null,
    "socialText": null,
    "street": "Eichgartenstraße 1",
    "subsection": null,
    "type": 2
}