{
    "CoordinateSystemType": "Unknown",
    "SectorType": 1,
    "city": "Aichstetten",
    "comments": null,
    "containerShape": null,
    "coordinates": "47.88485549487561,10.052981322262145",
    "dateEnd": "09/03/2024 11:57:17",
    "dateStart": "09/01/2024 23:59:35",
    "definition": null,
    "district": null,
    "geoType": 1,
    "houseNr": null,
    "id": 4330930,
    "idPublic": null,
    "internal": 0,
    "isFixed": false,
    "isOutageInArea": false,
    "lastUpdate": "09/03/2024 11:57:17",
    "liveInfo": "",
    "operatorId": 411,
    "operatorName": "Netze BW GmbH",
    "origin": 5,
    "photo": null,
    "postalCode": "88317",
    "radius": null,
    "social": null,
    "socialText": null,
    "street": null,
    "subsection": null,
    "type": 1
}