{
    "CoordinateSystemType": "Unknown",
    "SectorType": 1,
    "city": "Mittelhof",
    "comments": null,
    "containerShape": null,
    "coordinates": "50.77940092992197,7.759179198137229",
    "dateEnd": "11/29/2023 10:40:00",
    "dateStart": "11/29/2023 08:36:24",
    "definition": null,
    "district": null,
    "geoType": 1,
    "houseNr": null,
    "id": 3919604,
    "idPublic": null,
    "internal": 0,
    "isFixed": false,
    "isOutageInArea": false,
    "lastUpdate": "11/29/2023 08:45:31",
    "liveInfo": null,
    "operatorId": 216,
    "operatorName": "EAM Netz GmbH",
    "origin": 3,
    "photo": null,
    "postalCode": "57537",
    "radius": null,
    "social": null,
    "socialText": null,
    "street": null,
    "subsection": null,
    "type": 1
}