{
    "CoordinateSystemType": "Unknown",
    "SectorType": 1,
    "city": "Dortmund",
    "comments": null,
    "containerShape": null,
    "coordinates": "51.50960151742044,7.449804283587582",
    "dateEnd": "05/15/2024 16:05:00",
    "dateStart": "05/15/2024 14:03:38",
    "definition": null,
    "district": null,
    "geoType": 1,
    "houseNr": null,
    "id": 4130135,
    "idPublic": null,
    "internal": 0,
    "isFixed": false,
    "isOutageInArea": false,
    "lastUpdate": "05/15/2024 14:15:42",
    "liveInfo": null,
    "operatorId": 301,
    "operatorName": "Dortmunder Netz GmbH",
    "origin": 3,
    "photo": null,
    "postalCode": "44137",
    "radius": null,
    "social": null,
    "socialText": null,
    "street": null,
    "subsection": null,
    "type": 1
}