{
    "CoordinateSystemType": "Unknown",
    "SectorType": 1,
    "city": "Everswinkel",
    "comments": null,
    "containerShape": null,
    "coordinates": "51.91979461894301,7.852801993948434",
    "dateEnd": "01/19/2024 19:53:15",
    "dateStart": "01/19/2024 12:29:09",
    "definition": null,
    "district": null,
    "geoType": 1,
    "houseNr": null,
    "id": 3970853,
    "idPublic": null,
    "internal": 0,
    "isFixed": false,
    "isOutageInArea": false,
    "lastUpdate": "01/19/2024 19:53:15",
    "liveInfo": null,
    "operatorId": 132,
    "operatorName": "Westnetz GmbH",
    "origin": 5,
    "photo": null,
    "postalCode": "48351",
    "radius": null,
    "social": null,
    "socialText": null,
    "street": null,
    "subsection": null,
    "type": 1
}