{
    "CoordinateSystemType": "Unknown",
    "SectorType": 1,
    "city": "Bad Essen",
    "comments": null,
    "containerShape": null,
    "coordinates": "52.320026837308326,8.368317717390232",
    "dateEnd": "",
    "dateStart": "01/06/2024 16:34:05",
    "definition": null,
    "district": null,
    "geoType": 1,
    "houseNr": null,
    "id": 3962218,
    "idPublic": null,
    "internal": 0,
    "isFixed": false,
    "isOutageInArea": false,
    "lastUpdate": "01/07/2024 10:53:28",
    "liveInfo": null,
    "operatorId": 132,
    "operatorName": "Westnetz GmbH",
    "origin": 5,
    "photo": null,
    "postalCode": "49152",
    "radius": null,
    "social": null,
    "socialText": null,
    "street": null,
    "subsection": null,
    "type": 1
}