{
    "CoordinateSystemType": "Unknown",
    "SectorType": 1,
    "city": "Tating",
    "comments": null,
    "containerShape": null,
    "coordinates": "54.32382528835426,8.70799041706454",
    "dateEnd": "05/28/2024 04:15:00",
    "dateStart": "05/28/2024 02:12:06",
    "definition": null,
    "district": null,
    "geoType": 1,
    "houseNr": null,
    "id": 4150585,
    "idPublic": null,
    "internal": 0,
    "isFixed": false,
    "isOutageInArea": false,
    "lastUpdate": "05/28/2024 03:18:14",
    "liveInfo": null,
    "operatorId": 120,
    "operatorName": "Schleswig-Holstein Netz AG",
    "origin": 3,
    "photo": null,
    "postalCode": "25881",
    "radius": null,
    "social": null,
    "socialText": null,
    "street": null,
    "subsection": null,
    "type": 1
}