{
    "CoordinateSystemType": "Unknown",
    "SectorType": 1,
    "city": "Hellertshausen",
    "comments": null,
    "containerShape": null,
    "coordinates": "49.80809995126844,7.239297567640517",
    "dateEnd": "09/18/2024 13:00:00",
    "dateStart": "09/18/2024 09:00:00",
    "definition": null,
    "district": null,
    "geoType": 1,
    "houseNr": null,
    "id": 4368824,
    "idPublic": null,
    "internal": 0,
    "isFixed": false,
    "isOutageInArea": false,
    "lastUpdate": "09/18/2024 11:55:21",
    "liveInfo": null,
    "operatorId": 132,
    "operatorName": "Westnetz GmbH",
    "origin": 5,
    "photo": null,
    "postalCode": "55758",
    "radius": null,
    "social": null,
    "socialText": null,
    "street": null,
    "subsection": null,
    "type": 2
}