{
    "CoordinateSystemType": "Unknown",
    "SectorType": 1,
    "city": "Wedemark",
    "comments": null,
    "containerShape": null,
    "coordinates": "52.55821887487922,9.708631395612997",
    "dateEnd": "09/29/2023 12:00:00",
    "dateStart": "09/29/2023 08:57:09",
    "definition": null,
    "district": null,
    "geoType": 1,
    "houseNr": null,
    "id": 3886822,
    "idPublic": null,
    "internal": 0,
    "isFixed": false,
    "isOutageInArea": false,
    "lastUpdate": "09/29/2023 08:57:09",
    "liveInfo": null,
    "operatorId": 42,
    "operatorName": "Avacon AG",
    "origin": 3,
    "photo": null,
    "postalCode": "30900",
    "radius": null,
    "social": null,
    "socialText": null,
    "street": null,
    "subsection": null,
    "type": 1
}