{
    "CoordinateSystemType": "Unknown",
    "SectorType": 1,
    "city": "Neuenkirchen",
    "comments": null,
    "containerShape": null,
    "coordinates": "52.1977220207254,7.427364555281582",
    "dateEnd": "11/02/2023 19:55:01",
    "dateStart": "11/02/2023 13:42:28",
    "definition": null,
    "district": null,
    "geoType": 1,
    "houseNr": null,
    "id": 3904735,
    "idPublic": null,
    "internal": 0,
    "isFixed": false,
    "isOutageInArea": false,
    "lastUpdate": "11/02/2023 19:55:01",
    "liveInfo": null,
    "operatorId": 132,
    "operatorName": "Westnetz GmbH",
    "origin": 5,
    "photo": null,
    "postalCode": "48485",
    "radius": null,
    "social": null,
    "socialText": null,
    "street": null,
    "subsection": null,
    "type": 1
}