{
    "CoordinateSystemType": "Unknown",
    "SectorType": 1,
    "city": "Ellingstedt",
    "comments": null,
    "containerShape": null,
    "coordinates": "54.47894277253512,9.409998477893197",
    "dateEnd": "02/27/2024 07:20:00",
    "dateStart": "02/27/2024 05:18:02",
    "definition": null,
    "district": null,
    "geoType": 1,
    "houseNr": null,
    "id": 4008882,
    "idPublic": null,
    "internal": 0,
    "isFixed": false,
    "isOutageInArea": false,
    "lastUpdate": "02/27/2024 06:36:06",
    "liveInfo": null,
    "operatorId": 120,
    "operatorName": "Schleswig-Holstein Netz AG",
    "origin": 3,
    "photo": null,
    "postalCode": "24870",
    "radius": null,
    "social": null,
    "socialText": null,
    "street": null,
    "subsection": null,
    "type": 1
}