{
    "CoordinateSystemType": "Unknown",
    "SectorType": 1,
    "city": "Scharbeutz",
    "comments": null,
    "containerShape": null,
    "coordinates": "54.055022459872916,10.738716726269821",
    "dateEnd": "11/18/2023 02:21:05",
    "dateStart": "11/17/2023 09:48:09",
    "definition": null,
    "district": null,
    "geoType": 1,
    "houseNr": null,
    "id": 3912026,
    "idPublic": null,
    "internal": 0,
    "isFixed": false,
    "isOutageInArea": false,
    "lastUpdate": "11/18/2023 02:21:05",
    "liveInfo": null,
    "operatorId": 132,
    "operatorName": "Westnetz GmbH",
    "origin": 5,
    "photo": null,
    "postalCode": "23683",
    "radius": null,
    "social": null,
    "socialText": null,
    "street": null,
    "subsection": null,
    "type": 1
}