{
    "CoordinateSystemType": "Unknown",
    "SectorType": 1,
    "city": "Morbach",
    "comments": null,
    "containerShape": null,
    "coordinates": "49.81470874037763,7.116310143174949",
    "dateEnd": "06/12/2024 11:51:02",
    "dateStart": "06/11/2024 06:24:05",
    "definition": null,
    "district": null,
    "geoType": 1,
    "houseNr": null,
    "id": 4179645,
    "idPublic": null,
    "internal": 0,
    "isFixed": false,
    "isOutageInArea": false,
    "lastUpdate": "06/12/2024 11:51:02",
    "liveInfo": null,
    "operatorId": 132,
    "operatorName": "Westnetz GmbH",
    "origin": 5,
    "photo": null,
    "postalCode": "54497",
    "radius": null,
    "social": null,
    "socialText": null,
    "street": null,
    "subsection": null,
    "type": 1
}