{
    "CoordinateSystemType": "Unknown",
    "SectorType": 1,
    "city": "Schmieritz",
    "comments": null,
    "containerShape": null,
    "coordinates": "50.71923853660053,11.800801139173767",
    "dateEnd": "06/30/2024 11:55:11",
    "dateStart": "06/30/2024 07:49:00",
    "definition": null,
    "district": null,
    "geoType": 1,
    "houseNr": null,
    "id": 4217592,
    "idPublic": null,
    "internal": 0,
    "isFixed": false,
    "isOutageInArea": false,
    "lastUpdate": "06/30/2024 11:55:11",
    "liveInfo": null,
    "operatorId": 30,
    "operatorName": "TEN Thüringer Energienetze GmbH & Co. KG",
    "origin": 1,
    "photo": null,
    "postalCode": "07819",
    "radius": null,
    "social": null,
    "socialText": null,
    "street": null,
    "subsection": null,
    "type": 1
}