{
    "CoordinateSystemType": "Unknown",
    "SectorType": 1,
    "city": "Griesstätt",
    "comments": null,
    "containerShape": null,
    "coordinates": "47.9795000,12.1838000",
    "dateEnd": "12/02/2023 19:55:31",
    "dateStart": "12/02/2023 06:46:28",
    "definition": null,
    "district": null,
    "geoType": 2,
    "houseNr": null,
    "id": 3925688,
    "idPublic": null,
    "internal": 0,
    "isFixed": false,
    "isOutageInArea": false,
    "lastUpdate": "12/02/2023 19:55:31",
    "liveInfo": null,
    "operatorId": 402,
    "operatorName": "Bayernwerk Netz GmbH",
    "origin": 1,
    "photo": null,
    "postalCode": "83556",
    "radius": 1000,
    "social": null,
    "socialText": null,
    "street": null,
    "subsection": null,
    "type": 1
}