{
    "CoordinateSystemType": "Unknown",
    "SectorType": 1,
    "city": "Frankenroda",
    "comments": null,
    "containerShape": null,
    "coordinates": "51.09441564880507,10.27883818714183",
    "dateEnd": "11/24/2023 19:25:00",
    "dateStart": "11/24/2023 17:24:46",
    "definition": null,
    "district": null,
    "geoType": 1,
    "houseNr": null,
    "id": 3916553,
    "idPublic": null,
    "internal": 0,
    "isFixed": false,
    "isOutageInArea": false,
    "lastUpdate": "11/24/2023 18:21:12",
    "liveInfo": null,
    "operatorId": 30,
    "operatorName": "TEN Thüringer Energienetze GmbH & Co. KG",
    "origin": 3,
    "photo": null,
    "postalCode": "99826",
    "radius": null,
    "social": null,
    "socialText": null,
    "street": null,
    "subsection": null,
    "type": 1
}