{
    "CoordinateSystemType": "Unknown",
    "SectorType": 1,
    "city": "Frechen",
    "comments": null,
    "containerShape": null,
    "coordinates": "50.91800135630654,6.813459841395167",
    "dateEnd": "05/20/2024 20:56:52",
    "dateStart": "05/20/2024 07:22:15",
    "definition": null,
    "district": null,
    "geoType": 1,
    "houseNr": null,
    "id": 4136826,
    "idPublic": null,
    "internal": 0,
    "isFixed": false,
    "isOutageInArea": false,
    "lastUpdate": "05/20/2024 20:56:53",
    "liveInfo": null,
    "operatorId": 132,
    "operatorName": "Westnetz GmbH",
    "origin": 5,
    "photo": null,
    "postalCode": "50226",
    "radius": null,
    "social": null,
    "socialText": null,
    "street": null,
    "subsection": null,
    "type": 1
}