{
    "CoordinateSystemType": "Unknown",
    "SectorType": 1,
    "city": "Essen",
    "comments": null,
    "containerShape": null,
    "coordinates": "51.478379619983215,6.928894989124788",
    "dateEnd": "",
    "dateStart": "01/12/2024 01:59:45",
    "definition": null,
    "district": null,
    "geoType": 1,
    "houseNr": null,
    "id": 3965624,
    "idPublic": null,
    "internal": 0,
    "isFixed": false,
    "isOutageInArea": false,
    "lastUpdate": "01/12/2024 02:13:23",
    "liveInfo": null,
    "operatorId": 132,
    "operatorName": "Westnetz GmbH",
    "origin": 5,
    "photo": null,
    "postalCode": "45357",
    "radius": null,
    "social": null,
    "socialText": null,
    "street": null,
    "subsection": null,
    "type": 1
}