{
    "CoordinateSystemType": "Unknown",
    "SectorType": 1,
    "city": "Simmerath",
    "comments": null,
    "containerShape": null,
    "coordinates": "50.59341684221173,6.29194471454671",
    "dateEnd": "12/22/2023 02:50:00",
    "dateStart": "12/22/2023 00:45:31",
    "definition": null,
    "district": null,
    "geoType": 1,
    "houseNr": null,
    "id": 3950244,
    "idPublic": null,
    "internal": 0,
    "isFixed": false,
    "isOutageInArea": false,
    "lastUpdate": "12/22/2023 01:06:25",
    "liveInfo": null,
    "operatorId": 350,
    "operatorName": "Regionetz GmbH",
    "origin": 3,
    "photo": null,
    "postalCode": "52152",
    "radius": null,
    "social": null,
    "socialText": null,
    "street": null,
    "subsection": null,
    "type": 1
}