{
    "CoordinateSystemType": "Unknown",
    "SectorType": 1,
    "city": "Attenkirchen",
    "comments": null,
    "containerShape": null,
    "coordinates": "48.497932809354424,11.758708890016926",
    "dateEnd": "07/21/2024 22:00:00",
    "dateStart": "07/21/2024 19:57:22",
    "definition": null,
    "district": null,
    "geoType": 1,
    "houseNr": null,
    "id": 4254015,
    "idPublic": null,
    "internal": 0,
    "isFixed": false,
    "isOutageInArea": false,
    "lastUpdate": "07/21/2024 20:57:24",
    "liveInfo": null,
    "operatorId": 402,
    "operatorName": "Bayernwerk Netz GmbH",
    "origin": 3,
    "photo": null,
    "postalCode": "85395",
    "radius": null,
    "social": null,
    "socialText": null,
    "street": null,
    "subsection": null,
    "type": 1
}