{
    "CoordinateSystemType": "Unknown",
    "SectorType": 1,
    "city": "Obersulm",
    "comments": null,
    "containerShape": null,
    "coordinates": "49.14005524784708,9.403674189962233",
    "dateEnd": "09/25/2024 08:06:06",
    "dateStart": "09/25/2024 05:57:13",
    "definition": null,
    "district": null,
    "geoType": 1,
    "houseNr": null,
    "id": 4397449,
    "idPublic": null,
    "internal": 0,
    "isFixed": true,
    "isOutageInArea": false,
    "lastUpdate": "09/25/2024 08:06:06",
    "liveInfo": "",
    "operatorId": 411,
    "operatorName": "Netze BW GmbH",
    "origin": 5,
    "photo": null,
    "postalCode": "74182",
    "radius": null,
    "social": null,
    "socialText": null,
    "street": null,
    "subsection": null,
    "type": 1
}