{
    "CoordinateSystemType": "Unknown",
    "SectorType": 1,
    "city": "Eberswalde",
    "comments": null,
    "containerShape": null,
    "coordinates": "52.8373323,13.8086772",
    "dateEnd": "09/25/2024 18:30:25",
    "dateStart": "09/25/2024 15:26:00",
    "definition": null,
    "district": null,
    "geoType": 1,
    "houseNr": null,
    "id": 4399097,
    "idPublic": null,
    "internal": 0,
    "isFixed": true,
    "isOutageInArea": false,
    "lastUpdate": "09/25/2024 18:30:25",
    "liveInfo": null,
    "operatorId": 81,
    "operatorName": "E.DIS Netz GmbH",
    "origin": 1,
    "photo": null,
    "postalCode": "16225",
    "radius": 1000,
    "social": null,
    "socialText": null,
    "street": null,
    "subsection": null,
    "type": 1
}