{
    "CoordinateSystemType": "Unknown",
    "SectorType": 1,
    "city": "Münster",
    "comments": null,
    "containerShape": null,
    "coordinates": "51.96651996253385,7.615836780020396",
    "dateEnd": "11/20/2023 09:30:00",
    "dateStart": "11/20/2023 09:21:27",
    "definition": null,
    "district": null,
    "geoType": 1,
    "houseNr": null,
    "id": 3913239,
    "idPublic": null,
    "internal": 0,
    "isFixed": false,
    "isOutageInArea": false,
    "lastUpdate": "11/20/2023 09:21:28",
    "liveInfo": null,
    "operatorId": 324,
    "operatorName": "Stadtnetze Münster GmbH",
    "origin": 3,
    "photo": null,
    "postalCode": "48143",
    "radius": null,
    "social": null,
    "socialText": null,
    "street": null,
    "subsection": null,
    "type": 1
}