{
    "CoordinateSystemType": "Unknown",
    "SectorType": 1,
    "city": "Bremen",
    "comments": null,
    "containerShape": null,
    "coordinates": "53.051160,8.839050",
    "dateEnd": "11/20/2023 16:07:06",
    "dateStart": "11/20/2023 12:52:56",
    "definition": null,
    "district": "Habenhausen",
    "geoType": 2,
    "houseNr": null,
    "id": 3913652,
    "idPublic": null,
    "internal": 0,
    "isFixed": false,
    "isOutageInArea": false,
    "lastUpdate": "11/20/2023 16:07:06",
    "liveInfo": "Störungsbedingte Unterbechung Fellendsweg",
    "operatorId": 182,
    "operatorName": "wesernetz Bremen GmbH",
    "origin": 5,
    "photo": null,
    "postalCode": "28279",
    "radius": 300,
    "social": null,
    "socialText": null,
    "street": null,
    "subsection": null,
    "type": 1
}